my_ray_engine/__init__.py
my_ray_engine/engine.py
simpleraycast/__init__.py
simpleraycast/engine.py
simpleraycast-0.3.2.4.dist-info/METADATA
simpleraycast-0.3.2.4.dist-info/WHEEL
simpleraycast-0.3.2.4.dist-info/top_level.txt
simpleraycast-0.3.2.4.dist-info/RECORD
